[
  {
    "ContainingType": "SuperheroAPI.Controllers.SuperheroController",
    "Method": "GetSuperHero",
    "RelativePath": "api/Superhero/getAllHeroes",
    "HttpMethod": "GET",
    "IsController": true,
    "Order": 0,
    "Parameters": [],
    "ReturnTypes": [
      {
        "Type": "System.Collections.Generic.ICollection\u00601[[SuperheroAPI.Models.Superhero, SuperheroAPI, Version=1.0.0.0, Culture=neutral, PublicKeyToken=null]]",
        "MediaTypes": [
          "text/plain",
          "application/json",
          "text/json"
        ],
        "StatusCode": 200
      }
    ]
  }
]